openhcs/__init__.py
openhcs/components/__init__.py
openhcs/components/framework.py
openhcs/config_framework/__init__.py
openhcs/config_framework/cache_warming.py
openhcs/config_framework/config.py
openhcs/config_framework/context_manager.py
openhcs/config_framework/dual_axis_resolver.py
openhcs/config_framework/global_config.py
openhcs/config_framework/lazy_factory.py
openhcs/config_framework/placeholder.py
openhcs/constants/__init__.py
openhcs/constants/constants.py
openhcs/constants/input_source.py
openhcs/constants/streaming.py
openhcs/core/__init__.py
openhcs/core/auto_register_meta.py
openhcs/core/config.py
openhcs/core/config_cache.py
openhcs/core/lazy_gpu_imports.py
openhcs/core/lazy_placeholder.py
openhcs/core/lazy_placeholder_simplified.py
openhcs/core/log_utils.py
openhcs/core/metadata_cache.py
openhcs/core/path_cache.py
openhcs/core/registry_cache.py
openhcs/core/registry_discovery.py
openhcs/core/roi.py
openhcs/core/streaming_config_factory.py
openhcs/core/utils.py
openhcs/core/xdg_paths.py
openhcs/core/components/__init__.py
openhcs/core/components/metaprogramming.py
openhcs/core/components/multiprocessing.py
openhcs/core/components/parser_metaprogramming.py
openhcs/core/components/validation.py
openhcs/core/context/__init__.py
openhcs/core/context/processing_context.py
openhcs/core/memory/__init__.py
openhcs/core/memory/conversion_helpers.py
openhcs/core/memory/converters.py
openhcs/core/memory/decorators.py
openhcs/core/memory/dtype_scaling.py
openhcs/core/memory/exceptions.py
openhcs/core/memory/framework_config.py
openhcs/core/memory/framework_ops.py
openhcs/core/memory/gpu_cleanup.py
openhcs/core/memory/oom_recovery.py
openhcs/core/memory/slice_processing.py
openhcs/core/memory/stack_utils.py
openhcs/core/memory/utils.py
openhcs/core/orchestrator/__init__.py
openhcs/core/orchestrator/execution_result.py
openhcs/core/orchestrator/gpu_scheduler.py
openhcs/core/orchestrator/orchestrator.py
openhcs/core/pipeline/__init__.py
openhcs-0.4.5.dist-info/METADATA
openhcs-0.4.5.dist-info/WHEEL
openhcs-0.4.5.dist-info/entry_points.txt
openhcs-0.4.5.dist-info/top_level.txt
openhcs-0.4.5.dist-info/RECORD
