Metadata-Version: 2.4
Name: openhcs
Version: 0.4.5
Summary: High-Content Screening image processing engine with native GPU support
Author-email: Tristan Simas <tristan.simas@mail.mcgill.ca>
License: MIT License
Project-URL: Homepage, https://github.com/trissim/openhcs
Project-URL: Bug Reports, https://github.com/trissim/openhcs/issues
Project-URL: Source, https://github.com/trissim/openhcs
Project-URL: Documentation, https://github.com/trissim/openhcs/blob/main/README.md
Keywords: microscopy,image-processing,high-content-screening,gpu,computer-vision
Classifier: Development Status :: 3 - Alpha
Classifier: Intended Audience :: Science/Research
Classifier: Topic :: Scientific/Engineering :: Image Processing
Classifier: Topic :: Scientific/Engineering :: Bio-Informatics
Classifier: License :: OSI Approved :: MIT License
Classifier: Programming Language :: Python :: 3
Classifier: Programming Language :: Python :: 3.11
Classifier: Programming Language :: Python :: 3.12
Classifier: Operating System :: OS Independent
Requires-Python: >=3.11
Requires-Dist: numpy>=1.26.4
Requires-Dist: scikit-image>=0.25.2
Requires-Dist: scikit-learn>=1.7.1
Requires-Dist: scipy>=1.12.0
Requires-Dist: pandas>=2.3.1
Requires-Dist: imageio>=2.37.0
Requires-Dist: tifffile>=2025.6.11
Requires-Dist: imagecodecs>=2025.3.30
Requires-Dist: opencv-python>=4.11.0.86
Requires-Dist: Multi-Template-Matching>=2.0.1
Requires-Dist: roifile>=2024.5.24
Requires-Dist: PyYAML>=6.0.2
Requires-Dist: zarr<3.0,>=2.18.7
Requires-Dist: ome-zarr>=0.11.1
Requires-Dist: dill>=0.4.0
Requires-Dist: setuptools
Requires-Dist: watchdog>=6.0.0
Requires-Dist: portalocker>=2.8.2
Requires-Dist: psutil>=5.9.0
Provides-Extra: dev
Requires-Dist: pytest>=7.4.0; extra == "dev"
Requires-Dist: pytest-cov>=4.1.0; extra == "dev"
Requires-Dist: coverage>=7.3.2; extra == "dev"
Requires-Dist: genbadge[coverage]; extra == "dev"
Requires-Dist: pytest-asyncio>=0.21.0; extra == "dev"
Requires-Dist: pyzmq>=26.0.0; extra == "dev"
Provides-Extra: dev-gui
Requires-Dist: pytest-qt>=4.2.0; extra == "dev-gui"
Provides-Extra: gui
Requires-Dist: PyQt6>=6.9.1; extra == "gui"
Requires-Dist: PyQt6-QScintilla>=2.14.1; extra == "gui"
Requires-Dist: pyqtgraph>=0.13.7; extra == "gui"
Requires-Dist: GPUtil>=1.4.0; extra == "gui"
Provides-Extra: napari
Requires-Dist: napari>=0.4.18; extra == "napari"
Requires-Dist: napari-roi-manager>=0.0.6; extra == "napari"
Provides-Extra: fiji
Requires-Dist: pyimagej>=1.4.1; extra == "fiji"
Requires-Dist: scyjava>=1.9.1; extra == "fiji"
Provides-Extra: viz
Requires-Dist: napari>=0.4.18; extra == "viz"
Requires-Dist: napari-roi-manager>=0.0.6; extra == "viz"
Requires-Dist: pyimagej>=1.4.1; extra == "viz"
Requires-Dist: scyjava>=1.9.1; extra == "viz"
Provides-Extra: omero
Requires-Dist: omero-py>=5.19.0; extra == "omero"
Provides-Extra: docs
Requires-Dist: sphinx>=4.0.0; extra == "docs"
Requires-Dist: sphinx-rtd-theme>=1.0.0; extra == "docs"
Requires-Dist: sphinx-toolbox>=3.0.0; extra == "docs"
Requires-Dist: sphinx-design>=0.5.0; extra == "docs"
Provides-Extra: remote
Requires-Dist: pyzmq>=26.0.0; extra == "remote"
Requires-Dist: omero-py>=5.19.0; extra == "remote"
Provides-Extra: gpu
Requires-Dist: torch<2.8.0,>=2.6.0; extra == "gpu"
Requires-Dist: torchvision<0.23.0,>=0.21.0; extra == "gpu"
Requires-Dist: jax<0.6.0,>=0.5.3; extra == "gpu"
Requires-Dist: jaxlib<0.6.0,>=0.5.3; extra == "gpu"
Requires-Dist: jax-cuda12-pjrt<0.6.0,>=0.5.3; extra == "gpu"
Requires-Dist: jax-cuda12-plugin<0.6.0,>=0.5.3; extra == "gpu"
Requires-Dist: cupy-cuda12x<14.0.0,>=13.3.0; extra == "gpu"
Requires-Dist: cucim-cu12<26.0.0,>=25.6.0; extra == "gpu"
Requires-Dist: tensorflow<2.20.0,>=2.19.0; extra == "gpu"
Requires-Dist: tensorflow-probability[tf]<0.26.0,>=0.25.0; extra == "gpu"
Requires-Dist: pyclesperanto>=0.17.1; extra == "gpu"
Provides-Extra: all
Requires-Dist: PyQt6>=6.9.1; extra == "all"
Requires-Dist: PyQt6-QScintilla>=2.14.1; extra == "all"
Requires-Dist: pyqtgraph>=0.13.7; extra == "all"
Requires-Dist: GPUtil>=1.4.0; extra == "all"
Requires-Dist: napari>=0.4.18; extra == "all"
Requires-Dist: napari-roi-manager>=0.0.6; extra == "all"
Requires-Dist: pyimagej>=1.4.1; extra == "all"
Requires-Dist: scyjava>=1.9.1; extra == "all"
Requires-Dist: torch<2.8.0,>=2.6.0; extra == "all"
Requires-Dist: torchvision<0.23.0,>=0.21.0; extra == "all"
Requires-Dist: jax<0.6.0,>=0.5.3; extra == "all"
Requires-Dist: jaxlib<0.6.0,>=0.5.3; extra == "all"
Requires-Dist: jax-cuda12-pjrt<0.6.0,>=0.5.3; extra == "all"
Requires-Dist: jax-cuda12-plugin<0.6.0,>=0.5.3; extra == "all"
Requires-Dist: cupy-cuda12x<14.0.0,>=13.3.0; extra == "all"
Requires-Dist: cucim-cu12<26.0.0,>=25.6.0; extra == "all"
Requires-Dist: tensorflow<2.20.0,>=2.19.0; extra == "all"
Requires-Dist: tensorflow-probability[tf]<0.26.0,>=0.25.0; extra == "all"
Requires-Dist: pyclesperanto>=0.17.1; extra == "all"
